rqbit_client/__init__.py
rqbit_client/client.py
rqbit_client/exceptions.py
rqbit_client/models.py
rqbit_client-0.0.2.dist-info/licenses/LICENSE
rqbit_client-0.0.2.dist-info/WHEEL
rqbit_client-0.0.2.dist-info/METADATA
rqbit_client-0.0.2.dist-info/RECORD
