Metadata-Version: 2.4
Name: rqbit-client
Version: 0.0.2
Summary: Python client for rqbit bittorent web api
License-Expression: MIT
License-File: LICENSE
Classifier: Development Status :: 3 - Alpha
Classifier: Programming Language :: Python :: 3
Classifier: Programming Language :: Python :: 3.10
Classifier: Programming Language :: Python :: 3.11
Classifier: Programming Language :: Python :: 3.12
Classifier: Programming Language :: Python :: 3.13
Classifier: Programming Language :: Python :: 3.14
Requires-Dist: httpx>=0.27.0
Requires-Python: >=3.10
Project-URL: Repository, https://github.com/kviktor/rqbit-client
